jaxknife/__init__.py
jaxknife/bootstrap.py
jaxknife/jaxknife.py
jaxknife/stats_funcs.py
jaxknife-1.0.dist-info/LICENSE
jaxknife-1.0.dist-info/METADATA
jaxknife-1.0.dist-info/WHEEL
jaxknife-1.0.dist-info/top_level.txt
jaxknife-1.0.dist-info/RECORD
