Metadata-Version: 2.1
Name: jaxknife
Version: 1.0
License-File: LICENSE
Requires-Dist: jax
Requires-Dist: jaxlib
Requires-Dist: numpy
